pystq/constants.py
pystq/detector.py
pystq/materials.py
pystq/noise.py
pystq/score.py
pystq/sites.py
pystq/utils.py
pystq/widget.py
pystq-1.0.0.dist-info/METADATA
pystq-1.0.0.dist-info/WHEEL
pystq-1.0.0.dist-info/top_level.txt
pystq-1.0.0.dist-info/RECORD
