Metadata-Version: 2.1
Name: pystq
Version: 1.0.0
Summary: 
Home-page: https://github.com/gwoptics/SpacePyQuest
Author: Philip Jones, Isobel Romero-Shaw, Roshni Vincent, Andreas Freise
Author-email: isobel.romeroshaw@gmail.com
License: GPL 3
Platform: UNKNOWN
Classifier: Programming Language :: Python :: 3.7
Classifier: License :: OSI Approved :: GNU General Public License v3 or later (GPLv3+)
Classifier: Operating System :: OS Independent
Requires-Dist: bokeh (>=0.12.9)
Requires-Dist: jupyter
